{
    "after": [
        [
            {
                "comments": "",
                "id": 129,
                "length": 0,
                "order": 7,
                "seque": false,
                "set": 558
            },
            1
        ],
        [
            {
                "comments": "",
                "id": 99,
                "length": 246,
                "order": 14,
                "seque": false,
                "set": 386
            },
            1
        ],
        [
            {
                "comments": "",
                "id": 223,
                "length": 197,
                "order": 4,
                "seque": false,
                "set": 678
            },
            1
        ],
        [
            {
                "comments": "",
                "id": 28,
                "length": 308,
                "order": 9,
                "seque": false,
                "set": 785
            },
            1
        ],
        [
            {
                "comments": "",
                "id": 206,
                "length": 436,
                "order": 9,
                "seque": false,
                "set": 27
            },
            1
        ]
    ],
    "before": [
        [
            {
                "comments": "",
                "id": 129,
                "length": 0,
                "order": 7,
                "seque": false,
                "set": 558
            },
            1
        ],
        [
            {
                "comments": "",
                "id": 99,
                "length": 246,
                "order": 14,
                "seque": false,
                "set": 386
            },
            1
        ],
        [
            {
                "comments": "",
                "id": 223,
                "length": 197,
                "order": 4,
                "seque": false,
                "set": 678
            },
            1
        ],
        [
            {
                "comments": "",
                "id": 28,
                "length": 308,
                "order": 9,
                "seque": false,
                "set": 785
            },
            1
        ],
        [
            {
                "comments": "",
                "id": 206,
                "length": 436,
                "order": 9,
                "seque": false,
                "set": 27
            },
            1
        ]
    ],
    "longest": [
        [
            364,
            {
                "comments": "",
                "id": 140,
                "length": 364,
                "order": 1,
                "seque": false,
                "set": 730
            }
        ],
        [
            495,
            {
                "comments": "",
                "id": 140,
                "length": 495,
                "order": 15,
                "seque": false,
                "set": 386
            }
        ],
        [
            551,
            {
                "comments": "",
                "id": 140,
                "length": 551,
                "order": 9,
                "seque": true,
                "set": 264
            }
        ],
        [
            638,
            {
                "comments": "",
                "id": 140,
                "length": 638,
                "order": 1,
                "seque": false,
                "set": 1048
            }
        ],
        [
            641,
            {
                "comments": "",
                "id": 140,
                "length": 641,
                "order": 10,
                "seque": false,
                "set": 27
            }
        ]
    ],
    "name": "Here Comes Sunshine",
    "played": 10,
    "shortest": [
        [
            855,
            {
                "comments": "",
                "id": 140,
                "length": 855,
                "order": 10,
                "seque": false,
                "set": 785
            }
        ],
        [
            748,
            {
                "comments": "",
                "id": 140,
                "length": 748,
                "order": 5,
                "seque": false,
                "set": 678
            }
        ],
        [
            682,
            {
                "comments": "",
                "id": 140,
                "length": 682,
                "order": 1,
                "seque": false,
                "set": 832
            }
        ],
        [
            641,
            {
                "comments": "",
                "id": 140,
                "length": 641,
                "order": 10,
                "seque": false,
                "set": 27
            }
        ],
        [
            638,
            {
                "comments": "",
                "id": 140,
                "length": 638,
                "order": 1,
                "seque": false,
                "set": 1048
            }
        ]
    ],
    "years": [
        0,
        0,
        0,
        0,
        0,
        0,
        0,
        0,
        9,
        0,
        0,
        0,
        0,
        0,
        0,
        0,
        0,
        0,
        0,
        0,
        0,
        0,
        0,
        0,
        0,
        0,
        0,
        0,
        0,
        1,
        0
    ],
    "years_percent": [
        0,
        0,
        0,
        0,
        0,
        0,
        0,
        0,
        0,
        0,
        0,
        0,
        0,
        0,
        0,
        0,
        0,
        0,
        0,
        0,
        0,
        0,
        0,
        0,
        0,
        0,
        0,
        0,
        0,
        0,
        0
    ]
}