{
    "after": [
        [
            {
                "comments": "",
                "id": 94,
                "length": 237,
                "order": 1,
                "seque": true,
                "set": 1003
            },
            1
        ]
    ],
    "before": [
        [
            {
                "comments": "",
                "id": 94,
                "length": 237,
                "order": 1,
                "seque": true,
                "set": 1003
            },
            1
        ]
    ],
    "longest": [
        [
            322,
            {
                "comments": "",
                "id": 234,
                "length": 322,
                "order": 2,
                "seque": true,
                "set": 1003
            }
        ]
    ],
    "name": "Mountains Of The Moon",
    "played": 1,
    "shortest": [
        [
            322,
            {
                "comments": "",
                "id": 234,
                "length": 322,
                "order": 2,
                "seque": true,
                "set": 1003
            }
        ]
    ],
    "years": [
        0,
        0,
        0,
        0,
        1,
        0,
        0,
        0,
        0,
        0,
        0,
        0,
        0,
        0,
        0,
        0,
        0,
        0,
        0,
        0,
        0,
        0,
        0,
        0,
        0,
        0,
        0,
        0,
        0,
        0,
        0
    ],
    "years_percent": [
        0,
        0,
        0,
        0,
        0,
        0,
        0,
        0,
        0,
        0,
        0,
        0,
        0,
        0,
        0,
        0,
        0,
        0,
        0,
        0,
        0,
        0,
        0,
        0,
        0,
        0,
        0,
        0,
        0,
        0,
        0
    ]
}