{
    "after": [
        [
            {
                "comments": "",
                "id": 88,
                "length": 175,
                "order": 2,
                "seque": false,
                "set": 457
            },
            1
        ]
    ],
    "before": [
        [
            {
                "comments": "",
                "id": 88,
                "length": 175,
                "order": 2,
                "seque": false,
                "set": 457
            },
            1
        ]
    ],
    "longest": [
        [
            258,
            {
                "comments": "",
                "id": 296,
                "length": 258,
                "order": 3,
                "seque": false,
                "set": 457
            }
        ]
    ],
    "name": "Silver Threads & Golden Needles",
    "played": 1,
    "shortest": [
        [
            258,
            {
                "comments": "",
                "id": 296,
                "length": 258,
                "order": 3,
                "seque": false,
                "set": 457
            }
        ]
    ],
    "years": [
        0,
        0,
        0,
        0,
        0,
        1,
        0,
        0,
        0,
        0,
        0,
        0,
        0,
        0,
        0,
        0,
        0,
        0,
        0,
        0,
        0,
        0,
        0,
        0,
        0,
        0,
        0,
        0,
        0,
        0,
        0
    ],
    "years_percent": [
        0,
        0,
        0,
        0,
        0,
        0,
        0,
        0,
        0,
        0,
        0,
        0,
        0,
        0,
        0,
        0,
        0,
        0,
        0,
        0,
        0,
        0,
        0,
        0,
        0,
        0,
        0,
        0,
        0,
        0,
        0
    ]
}